PyFairnessAI/__init__.py
PyFairnessAI/data.py
PyFairnessAI/inprocessing.py
PyFairnessAI/metrics.py
PyFairnessAI/model_selection.py
PyFairnessAI/postprocessing.py
PyFairnessAI/preprocessing.py
PyFairnessAI/processing.py
PyFairnessAI-0.0.29.dist-info/LICENSE
PyFairnessAI-0.0.29.dist-info/METADATA
PyFairnessAI-0.0.29.dist-info/WHEEL
PyFairnessAI-0.0.29.dist-info/top_level.txt
PyFairnessAI-0.0.29.dist-info/RECORD
