Metadata-Version: 2.1
Name: PyFairnessAI
Version: 0.0.29
Summary: A Python package for fairness in AI and Machine Learning.
Home-page: https://github.com/FabioScielzoOrtiz/PyFairnessAI-package
Author: Fabio Scielzo Ortiz
Author-email: fabio.scielzoortiz@gmail.com
Classifier: Programming Language :: Python :: 3
Classifier: License :: OSI Approved :: MIT License
Classifier: Operating System :: OS Independent
Requires-Python: >=3.7
License-File: LICENSE
Requires-Dist: pandas
Requires-Dist: numpy
Requires-Dist: aif360
